vtzero/__init__.py
vtzero/cvtzero.pxd
vtzero/tile.cp310-win32.pyd
vtzero/tile.cpp
vtzero/tile.pyx
vtzero/version.py
vtzero-0.0.1b5.dist-info/METADATA
vtzero-0.0.1b5.dist-info/WHEEL
vtzero-0.0.1b5.dist-info/top_level.txt
vtzero-0.0.1b5.dist-info/RECORD
