Metadata-Version: 2.2
Name: vtzero
Version: 0.0.1b5
Summary: Python wrapper for vtzero C++ library.
Author: Yohan Boniface
Author-email: yohan.boniface@data.gouv.fr
License: MIT
Keywords: mvt mapbox vector tile gis
Platform: POSIX
Classifier: License :: OSI Approved :: MIT License
Classifier: Intended Audience :: Developers
Classifier: Programming Language :: Python :: 3
Classifier: Operating System :: POSIX
Classifier: Environment :: Web Environment
Classifier: Development Status :: 2 - Pre-Alpha
Classifier: Topic :: Scientific/Engineering :: GIS
Provides: vtzero
Requires-Python: >=3.8
Provides-Extra: test
Requires-Dist: pytest; extra == "test"
Requires-Dist: pytest-cov; extra == "test"
Dynamic: author
Dynamic: author-email
Dynamic: classifier
Dynamic: description
Dynamic: description-content-type
Dynamic: keywords
Dynamic: license
Dynamic: platform
Dynamic: provides
Dynamic: provides-extra
Dynamic: requires-python
Dynamic: summary
